Workbook

Sheet Main
A2: Sal | B2: 35000
B6: ITEM | C6: PRICE | D6: NOTE | E6: TOTAL
B7: Rent | C7: =3500 -> 3500 | D7: (Felix) | E7: =C7 -> 3500
B8: Transpo | C8: =Transpo!F14 -> 2640 | E8: =C8 -> 2640
B9: Food | C9: =NES!I17 -> 2820 | E9: =C9 -> 2820
B10: Laundry | C10: 200 | E10: =C10 -> 200
B11: Internet | C11: =WIFI!D8 -> 396 | D11: Load | E11: =C11 -> 396
B12: Water | C12: =0 -> 0 | E12: =C12 -> 0
B13: Utility | C13: =Table3513[[#Totals],[Cumulative Total]] -> 410 | E13: =C13 -> 410
D14: TOTAL | E14: =SUM(E7:E13) -> 9966 | F14: =SUM(E8:E12)/2 -> 3028
D15: Benefits | E15: =Benefits!B23 -> 800
D16: Gtotal | E16: =(B2+E15)-E14 -> 25834

Sheet Utility
G8: Monthly Cost | H8: Cumulative Total
G9: 510 | H9: =469 -> 469
G10: =G9-H9 -> 41 | H10: =G10*20 -> 820
H11: =H10/2 -> 410

Sheet Transpo
A1: Week | B1: Day | C1: Trip Type | D1: One-way Cost | E1: Back & Forth Cost | F1: Total Weekly Cost
A2: 1 | B2: Tue | C2: Office Onsite | D2: 120 | E2: 220 | F2: =SUM(E2:E4) -> 660
B3: Thu | C3: Office Onsite | D3: 120 | E3: 220
B4: Fri | C4: Office Onsite | D4: 120 | E4: 220
A5: 2 | B5: Tue | C5: Office Onsite | D5: 120 | E5: 220 | F5: =SUM(E5:E7) -> 660
B6: Thu | C6: Office Onsite | D6: 120 | E6: 220
B7: Fri | C7: Office Onsite | D7: 120 | E7: 220
A8: 3 | B8: Tue | C8: Office Onsite | D8: 120 | E8: 220 | F8: =SUM(E8:E10) -> 660
B9: Thu | C9: Office Onsite | D9: 120 | E9: 220
B10: Fri | C10: Office Onsite | D10: 120 | E10: 220
A11: 4 | B11: Tue | C11: Office Onsite | D11: 120 | E11: 220 | F11: =SUM(E11:E13) -> 660
B12: Thu | C12: Office Onsite | D12: 120 | E12: 220
B13: Fri | C13: Office Onsite | D13: 120 | E13: 220
A14: Total Monthly Cost | F14: =SUM(F2:F12) -> 2640

Sheet WIFI
A1: Info: | B1: Home Wifi + Globe Internet
B3: Week | C3: Weekly Cost | D3: Cumulative Total | J3: Note
B4: 1 | C4: 99 | J4: Smooth & Reliable for Most Work-from-Home Tasks | P4: Comfortable for Heavy Work or Multi-Device Setup
B5: 2 | C5: 99 | J5: 25–50 Mbps download | P5: 50–100+ Mbps download
B6: 3 | C6: 99 | J6: 5–10 Mbps upload | P6: 20+ Mbps upload
B7: 4 | C7: 99
C8: Total | D8: =SUM(C4:C7) -> 396
J10: Plan: Test your phone’s 5G If you get at least 2–3 bars somewhere indoors, a modem in that spot will likely perform better than your phone. If your phone shows 0–1 bar everywhere, a modem with an external antenna might help — otherwise, fiber might be the better main connection.
A11: Info: | B11: DITO 5G & for Home Wifi>10mbps
B13: Monthly Cost | C13: Cumulative Total | D13: Note | P13: DITO=Good => DITO only
B14: 999 | D14: UNLI 5G data 50GB 4G data *Unli on net, 300 mins off net *Unli Text to all mobile networ
B15: Total | C15: =SUM(B14:B14) -> 999
A19: Info: | B19: Postpaid & for Home Wifi>10mbps | D19: https://www.facebook.com/share/p/16np12oyqG/
D20: https://dito.ph/wowfi
B21: Monthly Cost | C21: Cumulative Total | D21: Note
B22: 888 | D22: UNLI 5G data 60GB 4G data *Unli on net *Unli Text to all mobile networ
B23: Total | C23: =SUM(B22:B22) -> 888
B28: ISP-FIBER | C28: MBPS | D28: MONTHLY
B29: Sky | C29: 100 | D29: 999 | F29: WIFI | G29: =(1000*24) + D8*(24) -> 33504
B30: KEJ Fiber | C30: 100 | D30: 1000 | F30: DITO | G30: =D34*(24-3)+745*(3) -> 33525
B31: Converge | C31: 100 | D31: 1250
B32: PLDT | C32: 100 | D32: 1299
B33: Globe | C33: 300 | D33: 1499
B34: DITO | C34: 500 | D34: 1490

Sheet Benefits
B2: BENEFIT
B3: NAME | C3: DESC | D3: TIME | E3: COST | F3: MONTHLY COST | G3: TOTAL PER MONTH | H3: SEMI-MONTHLY
B4: Wellness Allowance | C4: Annual Wellness Allowance of PHP 18,000 per year. | D4: YEARLY | E4: 18000 | F4: =Table7[[#This Row],[COST]]/12 -> 1500 | G4: =Table7[[#This Row],[MONTHLY COST]] -> 1500 | H4: =Table7[[#This Row],[TOTAL PER MONTH]]/2 -> 750
B5: Private Medical Insurance | C5: Per illness per year is Two Hundred Fifty Thousand Pesos (Php250,000.00), | D5: YEARLY | E5: 250000
B6: Rice Allowance | C6: Be eligible to a rice allowance of Two Thousand Pesos (Php 2,000.00) per month pro-rated on your first month. | D6: MONTHLY | E6: 2000 | F6: =Table7[[#This Row],[COST]] -> 2000 | G6: =Table7[[#This Row],[MONTHLY COST]] -> 2000 | H6: 0
B7: Meal Reimbursement overtime | C7: If you worked overtime from 6 PM to 10 PM on a Tuesday (4 hours), you can buy dinner worth up to ₱150, keep the OR, and claim it for reimbursement in payroll or through your company’s expense system. | D7: DAILY | E7: 150
B8: Transportation Subsidy | C8: Eligible to claim for transportation subsidy of Php 350 whenever they report physically to the office. | D8: DAILY | E8: 350 | F8: =12*Table7[[#This Row],[COST]] -> 4200 | G8: =Table7[[#This Row],[MONTHLY COST]] -> 4200
G10: =SUM(Table7[TOTAL PER MONTH]) -> 7700
B13: CONTRIBUTION
B14: NAME | C14: DESC | D14: COST
B15: SSS | C15: 0.05 | D15: =Main!$B$2*0.05 -> 1750
B16: PhilHealth | C16: 0.05 | D16: 450
B17: Pag-IBIG | C17: 0.02 | D17: 200
B18: (Income) Tax | C18: Tsal-3Total= 15% | D18: 4500 | F18: 28000 | G18: =17500 -> 17500
C19: TOTAL | D19: =SUM(D15:D18) -> 6900 | F19: =F18*0.15 -> 4200 | G19: =G18*2 -> 35000
B22: GTOTAL
B23: =G10-D19 -> 800

Sheet NES
D4: Week | E4: Day | F4: Trip Type | G4: One-way Cost | H4: Back & Forth Cost | I4: Total Weekly Cost
D5: 1 | E5: Tue | F5: Office Onsite | H5: =155 -> 155 | I5: =SUM(H5:H7) -> 465 | L5: =180+130 -> 310 | M5: =L5/2 -> 155
E6: Thu | F6: Office Onsite | G6: 120 | H6: =155 -> 155
E7: Fri | F7: Office Onsite | G7: 120 | H7: =155 -> 155
D8: 2 | E8: Tue | F8: Office Onsite | H8: =155 -> 155 | I8: =SUM(H8:H10) -> 465
E9: Thu | F9: Office Onsite | G9: 120 | H9: =155 -> 155
E10: Fri | F10: Office Onsite | G10: 120 | H10: =155 -> 155
D11: 3 | E11: Tue | F11: Office Onsite | H11: =155 -> 155 | I11: =SUM(H11:H13) -> 465
E12: Thu | F12: Office Onsite | G12: 120 | H12: =155 -> 155
E13: Fri | F13: Office Onsite | G13: 120 | H13: =155 -> 155
D14: 4 | E14: Tue | F14: Office Onsite | H14: =155 -> 155 | I14: =SUM(H14:H16) -> 465
E15: Thu | F15: Office Onsite | G15: 120 | H15: =155 -> 155
E16: Fri | F16: Office Onsite | G16: 120 | H16: =155 -> 155
D17: Total Monthly Cost | G17: =SUM(G5:G16) -> 960 | H17: =SUM(H5:H16) -> 1860 | I17: =SUM(Table212[[#This Row],[One-way Cost]:[Back & Forth Cost]]) -> 2820
